README.md
setup.py
materializationengine/__init__.py
materializationengine/admin.py
materializationengine/app.py
materializationengine/celery_init.py
materializationengine/celery_worker.py
materializationengine/chunkedgraph_gateway.py
materializationengine/config.py
materializationengine/database.py
materializationengine/errors.py
materializationengine/index_manager.py
materializationengine/info_client.py
materializationengine/models.py
materializationengine/schemas.py
materializationengine/shared_tasks.py
materializationengine/task_router.py
materializationengine/upsert.py
materializationengine/utils.py
materializationengine/views.py
materializationengine.egg-info/PKG-INFO
materializationengine.egg-info/SOURCES.txt
materializationengine.egg-info/dependency_links.txt
materializationengine.egg-info/requires.txt
materializationengine.egg-info/top_level.txt
materializationengine/blueprints/__init__.py
materializationengine/blueprints/reset_auth.py
materializationengine/blueprints/client/__init__.py
materializationengine/blueprints/client/api.py
materializationengine/blueprints/client/query.py
materializationengine/blueprints/client/schemas.py
materializationengine/blueprints/materialize/__init__.py
materializationengine/blueprints/materialize/api.py
materializationengine/workflows/__init__.py
materializationengine/workflows/bulk_upload.py
materializationengine/workflows/complete_workflow.py
materializationengine/workflows/create_frozen_database.py
materializationengine/workflows/dummy_workflow.py
materializationengine/workflows/ingest_new_annotations.py
materializationengine/workflows/periodic_database_removal.py
materializationengine/workflows/periodic_materialization.py
materializationengine/workflows/update_root_ids.py
tests/__init__.py
tests/conftest.py
tests/test_bulk_upload.py
tests/test_create_frozen_database.py
tests/test_database.py
tests/test_dummy_workflow.py
tests/test_index_manager.py
tests/test_ingest_new_annotations.py
tests/test_models.py
tests/test_shared_tasks.py
tests/test_update_root_ids.py