Metadata-Version: 2.1
Name: materializationengine
Version: 1.4.2
Summary: Combines DynamicAnnotationDB and PyChunkedGraph
Home-page: https://github.com/seung-lab/MaterializationEngine
Author: Forrest Collman
Author-email: forrestc@alleninstitute.org
License: UNKNOWN
Platform: UNKNOWN
Classifier: Programming Language :: Python :: 3
Classifier: License :: OSI Approved :: MIT License
Classifier: Operating System :: POSIX :: Linux
